syntax/__init__.py
syntax/abc.py
syntax/anon.py
syntax/autoimport.py
syntax/config_manager.py
syntax/decorators.py
syntax/extension_methods.py
syntax/maps.py
syntax/mdserver.py
syntax/quasi.py
syntax/serialize.py
syntax/server.py
syntax/snip.py
syntax/tests.py
syntax/utils.py
syntax-0.1.3.2.dist-info/DESCRIPTION.rst
syntax-0.1.3.2.dist-info/METADATA
syntax-0.1.3.2.dist-info/RECORD
syntax-0.1.3.2.dist-info/WHEEL
syntax-0.1.3.2.dist-info/metadata.json
syntax-0.1.3.2.dist-info/top_level.txt
