Metadata-Version: 2.0
Name: syntax
Version: 0.1.3.2
Summary: Simple utilities to extend the language and tools that come in handy
Home-page: http://github.com/Zantyr/syntax
Author: Zantyr
Author-email: tomasik.kwidzyn@gmail.com
License: MIT
Platform: UNKNOWN
Requires-Dist: gitpython
